google/cloud/orchestration/airflow/service/__init__.py
google/cloud/orchestration/airflow/service/gapic_version.py
google/cloud/orchestration/airflow/service/py.typed
google/cloud/orchestration/airflow/service_v1/__init__.py
google/cloud/orchestration/airflow/service_v1/gapic_metadata.json
google/cloud/orchestration/airflow/service_v1/gapic_version.py
google/cloud/orchestration/airflow/service_v1/py.typed
google/cloud/orchestration/airflow/service_v1/services/__init__.py
google/cloud/orchestration/airflow/service_v1/services/environments/__init__.py
google/cloud/orchestration/airflow/service_v1/services/environments/async_client.py
google/cloud/orchestration/airflow/service_v1/services/environments/client.py
google/cloud/orchestration/airflow/service_v1/services/environments/pagers.py
google/cloud/orchestration/airflow/service_v1/services/environments/transports/__init__.py
google/cloud/orchestration/airflow/service_v1/services/environments/transports/base.py
google/cloud/orchestration/airflow/service_v1/services/environments/transports/grpc.py
google/cloud/orchestration/airflow/service_v1/services/environments/transports/grpc_asyncio.py
google/cloud/orchestration/airflow/service_v1/services/environments/transports/rest.py
google/cloud/orchestration/airflow/service_v1/services/environments/transports/rest_base.py
google/cloud/orchestration/airflow/service_v1/services/image_versions/__init__.py
google/cloud/orchestration/airflow/service_v1/services/image_versions/async_client.py
google/cloud/orchestration/airflow/service_v1/services/image_versions/client.py
google/cloud/orchestration/airflow/service_v1/services/image_versions/pagers.py
google/cloud/orchestration/airflow/service_v1/services/image_versions/transports/__init__.py
google/cloud/orchestration/airflow/service_v1/services/image_versions/transports/base.py
google/cloud/orchestration/airflow/service_v1/services/image_versions/transports/grpc.py
google_cloud_orchestration_airflow-1.17.4.dist-info/LICENSE
google_cloud_orchestration_airflow-1.17.4.dist-info/METADATA
google_cloud_orchestration_airflow-1.17.4.dist-info/WHEEL
google_cloud_orchestration_airflow-1.17.4.dist-info/top_level.txt
google_cloud_orchestration_airflow-1.17.4.dist-info/RECORD
